relative_abundance/__init__.py
relative_abundance/calculate_abundance.py
relative_abundance/plotting_utils.py
test/__init__.py
test/test_math_functions.py
test/test_relative_abundance.py
RelativeAbundance-1.1.0.dist-info/METADATA
RelativeAbundance-1.1.0.dist-info/WHEEL
RelativeAbundance-1.1.0.dist-info/top_level.txt
RelativeAbundance-1.1.0.dist-info/RECORD
